agentrun_operation_sdk/cli/__init__.py
agentrun_operation_sdk/cli/cli.py
agentrun_operation_sdk/cli/common.py
agentrun_operation_sdk/cli/runtime/__init__.py
agentrun_operation_sdk/cli/runtime/commands.py
agentrun_operation_sdk/client/client.py
agentrun_operation_sdk/operations/runtime/__init__.py
agentrun_operation_sdk/operations/runtime/configure.py
agentrun_operation_sdk/operations/runtime/launch.py
agentrun_operation_sdk/operations/runtime/models.py
agentrun_operation_sdk/services/runtime.py
agentrun_operation_sdk/utils/logging_config.py
agentrun_operation_sdk/utils/runtime/config.py
agentrun_operation_sdk/utils/runtime/container.py
agentrun_operation_sdk/utils/runtime/entrypoint.py
agentrun_operation_sdk/utils/runtime/schema.py
agentrun_operation_sdk/utils/runtime/templates/Dockerfile.j2
agentrun_operation_sdk/utils/runtime/templates/dockerignore.template
agentrun_operation_sdk/utils/runtime/templates/execution_role_policy.json.j2
agentrun_operation_sdk/utils/runtime/templates/execution_role_trust_policy.json.j2
agentrun_sdk/__init__.py
agentrun_sdk/py.typed
agentrun_sdk/agent/__init__.py
agentrun_sdk/agent/agent.py
agentrun_sdk/agent/agent_result.py
agentrun_sdk/agent/state.py
agentrun_sdk/agent/conversation_manager/__init__.py
agentrun_sdk/agent/conversation_manager/conversation_manager.py
agentrun_sdk/agent/conversation_manager/null_conversation_manager.py
agentrun_sdk/agent/conversation_manager/sliding_window_conversation_manager.py
agentrun_sdk/agent/conversation_manager/summarizing_conversation_manager.py
agentrun_sdk/event_loop/__init__.py
agentrun_sdk/event_loop/event_loop.py
agentrun_sdk/event_loop/streaming.py
agentrun_sdk/experimental/__init__.py
agentrun_sdk/experimental/hooks/__init__.py
agentrun_sdk/experimental/hooks/events.py
agentrun_sdk/handlers/__init__.py
agentrun_sdk/handlers/callback_handler.py
agentrun_sdk/hooks/__init__.py
agentrun_sdk/hooks/events.py
agentrun_sdk/hooks/registry.py
agentrun_sdk/models/__init__.py
agentrun_sdk-0.1.3.dist-info/METADATA
agentrun_sdk-0.1.3.dist-info/WHEEL
agentrun_sdk-0.1.3.dist-info/entry_points.txt
agentrun_sdk-0.1.3.dist-info/top_level.txt
agentrun_sdk-0.1.3.dist-info/RECORD
